torchdyno/__init__.py
torchdyno/data/__init__.py
torchdyno/data/datasets/__init__.py
torchdyno/data/datasets/hhar.py
torchdyno/data/datasets/lorenz_system.py
torchdyno/data/datasets/memory_capacity.py
torchdyno/data/datasets/seq_mnist.py
torchdyno/data/datasets/wesad.py
torchdyno/data/utils/__init__.py
torchdyno/data/utils/seq_loader.py
torchdyno/models/__init__.py
torchdyno/models/esn/__init__.py
torchdyno/models/esn/esn.py
torchdyno/models/esn/reservoir.py
torchdyno/models/initializers.py
torchdyno/models/rnn_assembly/__init__.py
torchdyno/models/rnn_assembly/block_diagonal.py
torchdyno/models/rnn_assembly/rnn_assembly.py
torchdyno/models/rnn_assembly/skew_symm_coupling.py
torchdyno/optim/__init__.py
torchdyno/optim/intrinsic_plasticity.py
torchdyno/optim/ridge_regression.py
torchdyno-0.2.3.dist-info/LICENSE
torchdyno-0.2.3.dist-info/METADATA
torchdyno-0.2.3.dist-info/WHEEL
torchdyno-0.2.3.dist-info/RECORD
