Metadata-Version: 2.3
Name: torchdyno
Version: 0.2.3
Summary: A PyTorch-based library for Reservoir Computing and dynamical systems.
License: MIT
Author: Valerio De Caro
Author-email: valerio.decaro@di.unipi.it
Maintainer: Valerio De Caro
Maintainer-email: valerio.decaro@di.unipi.it
Requires-Python: >=3.10,<4.0
Classifier: License :: OSI Approved :: MIT License
Classifier: Programming Language :: Python :: 3
Classifier: Programming Language :: Python :: 3.10
Classifier: Programming Language :: Python :: 3.11
Classifier: Programming Language :: Python :: 3.12
Classifier: Programming Language :: Python :: 3.13
Requires-Dist: numpy (>=2.1.3,<3.0.0)
Requires-Dist: pandas (>=2.2.3,<3.0.0)
Requires-Dist: scipy (>=1.14.1,<2.0.0)
